turing.py
turing_coding-0.1.dist-info/METADATA
turing_coding-0.1.dist-info/WHEEL
turing_coding-0.1.dist-info/top_level.txt
turing_coding-0.1.dist-info/RECORD
