Metadata-Version: 2.1
Name: turing-coding
Version: 0.1
Summary: Guangzhou Turing EasyCoding
Home-page: UNKNOWN
Author: isnde
Author-email: isande@qq.com
License: UNKNOWN
Platform: UNKNOWN
Requires-Dist: pygame (==2.1.2)
Requires-Dist: Pillow (==9.3.0)
